todo_pkg/__init__.py
todo_pkg/todolist.py
todo_pkg/data/todo.db
todo_pkg/template/edit_task.tpl
todo_pkg/template/make_table.tpl
todo_pkg/template/new_task.tpl
todolist_JIANG.CHENG-0.0.1.dist-info/LICENSE
todolist_JIANG.CHENG-0.0.1.dist-info/METADATA
todolist_JIANG.CHENG-0.0.1.dist-info/WHEEL
todolist_JIANG.CHENG-0.0.1.dist-info/top_level.txt
todolist_JIANG.CHENG-0.0.1.dist-info/RECORD
